pygame_tools_tafh/__init__.py
pygame_tools_tafh/config.py
pygame_tools_tafh/engine.py
pygame_tools_tafh/game_object.py
pygame_tools_tafh/globals.py
pygame_tools_tafh/scene.py
pygame_tools_tafh/tween.py
pygame_tools_tafh/components/keybind.py
pygame_tools_tafh/components/movement.py
pygame_tools_tafh/components/sprite.py
pygame_tools_tafh/components/ui.py
pygame_tools_tafh/net/__init__.py
pygame_tools_tafh/net/host.py
pygame_tools_tafh/net/serialization.py
pygame_tools_tafh/vmath/__init__.py
pygame_tools_tafh/vmath/angle.py
pygame_tools_tafh/vmath/directions.py
pygame_tools_tafh/vmath/modx.py
pygame_tools_tafh/vmath/others.py
pygame_tools_tafh/vmath/vector.py
pygame_tools_tafh-0.1.3.dist-info/METADATA
pygame_tools_tafh-0.1.3.dist-info/WHEEL
pygame_tools_tafh-0.1.3.dist-info/licenses/LICENSE
pygame_tools_tafh-0.1.3.dist-info/RECORD
